setup.cfg
setup.py
scripts/g2h
scripts/h2g
vcsrosetta/__init__.py
vcsrosetta/print_translated_usage.py
vcsrosetta/usage_translator.py
vcsrosetta.egg-info/PKG-INFO
vcsrosetta.egg-info/SOURCES.txt
vcsrosetta.egg-info/dependency_links.txt
vcsrosetta.egg-info/top_level.txt
vcsrosetta/data/git_hg.yaml