Metadata-Version: 1.1
Name: vcsrosetta
Version: 0.1.1
Summary: Version Control System translator - includes g2h (git to hg) and h2g (hg to git)
Home-page: https://github.com/GreenGremlin/vcs-rosetta
Author: Jonathan Felchlin
Author-email: jonathan@xgecko.com
License: MIT
Download-URL: https://github.com/GreenGremlin/vcs-rosetta/tarball/0.1
Keywords: git,mercurial,hg,rosetta,translate,translation
Platform: UNKNOWN
Classifier: Development Status :: 3 - Alpha
Classifier: Intended Audience :: Developers
Classifier: Topic :: Software Development :: Documentation
Classifier: License :: OSI Approved :: MIT License
Classifier: Programming Language :: Python :: 2
Classifier: Programming Language :: Python :: 2.6
Classifier: Programming Language :: Python :: 2.7
Classifier: Programming Language :: Python :: 3
Classifier: Programming Language :: Python :: 3.2
Classifier: Programming Language :: Python :: 3.3
Classifier: Programming Language :: Python :: 3.4
